query_curve/__init__.py
query_curve/query_curve.py
query_curve/utils/__init__.py
query_curve/utils/decode.py
query_curve/utils/from_base_62.py
query_curve-0.1.0.dist-info/METADATA
query_curve-0.1.0.dist-info/WHEEL
query_curve-0.1.0.dist-info/licenses/LICENSE
query_curve-0.1.0.dist-info/RECORD
