Metadata-Version: 2.3
Name: query-curve
Version: 0.1.0
Summary: A query utility meant to query along a cubic bezier curve. Generate accompanying curve at https://querycurve.com
Project-URL: homepage, https://github.com/ralusek/query-curve/tree/main/repositories/query/python
Author-email: Tomas Savigliano <ralusek@gmail.com>
License: Copyright 2024 Tomas Savigliano
License-File: LICENSE
Classifier: License :: OSI Approved :: MIT License
Classifier: Operating System :: OS Independent
Classifier: Programming Language :: Python :: 3
Requires-Python: >=3.6
